cer/__init__.py
cer/cer.py
cer-1.2.0.dist-info/LICENSE
cer-1.2.0.dist-info/METADATA
cer-1.2.0.dist-info/WHEEL
cer-1.2.0.dist-info/entry_points.txt
cer-1.2.0.dist-info/top_level.txt
cer-1.2.0.dist-info/RECORD
