Metadata-Version: 2.1
Name: cer
Version: 1.2.0
Summary: Translation Edit Rate on the character level
Home-page: https://github.com/BramVanroy/CharacTER
Author: Bram Vanroy
Author-email: bramvanroy@hotmail.com
License: GPLv3
Project-URL: Issue tracker, https://github.com/BramVanroy/CharacTER/issues
Project-URL: Source, https://github.com/BramVanroy/CharacTER
Keywords: machine-translation machine-translation-evaluation evaluation mt
Classifier: Development Status :: 4 - Beta
Classifier: Intended Audience :: Developers
Classifier: Intended Audience :: Science/Research
Classifier: Topic :: Scientific/Engineering
Classifier: Topic :: Text Processing
Classifier: Programming Language :: Python :: 3.7
Classifier: Programming Language :: Python :: 3.8
Classifier: Programming Language :: Python :: 3.9
Classifier: Programming Language :: Python :: 3.10
Classifier: Operating System :: OS Independent
Classifier: License :: OSI Approved :: GNU General Public License v3 (GPLv3)
Requires-Python: >=3.7
License-File: LICENSE
Requires-Dist: Levenshtein
Provides-Extra: dev
Requires-Dist: isort (>=5.5.4) ; extra == 'dev'
Requires-Dist: black ; extra == 'dev'
Requires-Dist: flake8 ; extra == 'dev'
Requires-Dist: pytest ; extra == 'dev'
